genewiz_template_validator/__init__.py
genewiz_template_validator-0.0.11.data/scripts/validate_genewiz_templates
genewiz_template_validator-0.0.11.dist-info/METADATA
genewiz_template_validator-0.0.11.dist-info/WHEEL
genewiz_template_validator-0.0.11.dist-info/top_level.txt
genewiz_template_validator-0.0.11.dist-info/RECORD
