Metadata-Version: 2.1
Name: genewiz-template-validator
Version: 0.0.11
Summary: G001 data entry validation for Genewiz templates.
Home-page: UNKNOWN
Author: Greg Finak
Author-email: gfinak@fredhutch.org
License: MIT
Keywords: validation genewiz templates
Platform: UNKNOWN
Classifier: Development Status :: 3 - Alpha
Classifier: License :: OSI Approved :: MIT License
Classifier: Programming Language :: Python :: 2.7
Classifier: Topic :: Utilities
Requires-Dist: xlrd
